ltapysg/__init__.py
ltapysg/api.py
ltapysg/bus.py
ltapysg/exceptions.py
ltapysg/taxi.py
ltapysg/traffic.py
jsltapysg-0.0.3.dist-info/LICENSE
jsltapysg-0.0.3.dist-info/METADATA
jsltapysg-0.0.3.dist-info/WHEEL
jsltapysg-0.0.3.dist-info/top_level.txt
jsltapysg-0.0.3.dist-info/RECORD
